fid_tools-0.1.0.dist-info/licenses/LICENSE
pyfid/__init__.py
pyfid/core.py
fid_tools-0.1.0.dist-info/METADATA
fid_tools-0.1.0.dist-info/WHEEL
fid_tools-0.1.0.dist-info/top_level.txt
fid_tools-0.1.0.dist-info/RECORD
